fastda/__init__.py
fastda/version.py
fastda/hooks/__init__.py
fastda/hooks/training_hooks.py
fastda/loaders/__init__.py
fastda/loaders/builder.py
fastda/models/__init__.py
fastda/models/builder.py
fastda/models/optimizers/__init__.py
fastda/models/schedulers/__init__.py
fastda/models/schedulers/builder.py
fastda/models/schedulers/schedulers.py
fastda/models/utils/__init__.py
fastda/models/utils/gradient_reverse.py
fastda/runner/__init__.py
fastda/runner/builder.py
fastda/runner/trainer.py
fastda/runner/validator.py
fastda/utils/__init__.py
fastda/utils/arg_parser.py
fastda/utils/basic_utils.py
fastda/utils/collect_env.py
fastda/utils/logger.py
fastda/utils/metrics.py
fastda/utils/train_api.py
fastda/utils/writer.py
fastda-0.0.18.dist-info/LICENSE
fastda-0.0.18.dist-info/METADATA
fastda-0.0.18.dist-info/WHEEL
fastda-0.0.18.dist-info/top_level.txt
fastda-0.0.18.dist-info/RECORD
