Metadata-Version: 2.1
Name: fastda
Version: 0.0.18
Summary: A simple framework for unsupervised domain adaptation
Home-page: https://github.com/zhyx12/fastda
Author: Yixin Zhang
Author-email: zhyx12@mail.ustc.edu.cn
License: UNKNOWN
Platform: UNKNOWN
Classifier: Programming Language :: Python :: 3
Classifier: License :: OSI Approved :: MIT License
Classifier: Operating System :: OS Independent
License-File: LICENSE
